README.txt
setup.py
csFIFO/__init__.py
csFIFO/csFIFO.py
csFIFO/testFIFO.py
csFIFO/version.py
csFIFO.egg-info/PKG-INFO
csFIFO.egg-info/SOURCES.txt
csFIFO.egg-info/dependency_links.txt
csFIFO.egg-info/top_level.txt