Metadata-Version: 1.0
Name: csFIFO
Version: 1.3
Summary: A simple cStringIO based FIFO, implemented as a circular buffer
Home-page: http://pypi.python.org/pypi/csFIFO
Author: Jason Morgan
Author-email: pypi@cropwell.net
License: http://creativecommons.org/licenses/by-sa/3.0/
Keywords: FIFO
Platform: any
Classifier: Development Status :: 3 - Alpha
Classifier: Topic :: Software Development :: Libraries :: Python Modules
Classifier: Intended Audience :: Developers
Classifier: License :: Other/Proprietary License
Classifier: Operating System :: OS Independent
Classifier: Programming Language :: Python
